setup.py
decora/BDAddr.py
decora/BluetoothSocket.py
decora/__init__.py
decora.egg-info/PKG-INFO
decora.egg-info/SOURCES.txt
decora.egg-info/dependency_links.txt
decora.egg-info/not-zip-safe
decora.egg-info/requires.txt
decora.egg-info/top_level.txt